flas_cpp.cpython-312-darwin.so
vc_flas/metrics.py
vc_flas/__init__.py
vc_flas-0.1.7.dist-info/RECORD
vc_flas-0.1.7.dist-info/LICENSE
vc_flas-0.1.7.dist-info/WHEEL
vc_flas-0.1.7.dist-info/top_level.txt
vc_flas-0.1.7.dist-info/METADATA
