Metadata-Version: 2.1
Name: vc_flas
Version: 0.1.7
Summary: Python implementation of the Fast Linear Assigment Sorting Algorithm
Author: Nico Hezel, Konstantin Schall, Prof. Kai Uwe Barthel, Prof. Klaus Jung
Author-email: Bruno Schilling <bruno.schilling@htw-berlin.de>
License: Apache License
Project-URL: Homepage, https://github.com/Visual-Computing/LAS_FLAS/tree/main
Keywords: sorting,images
Classifier: Development Status :: 2 - Pre-Alpha
Classifier: Intended Audience :: Developers
Classifier: Programming Language :: Python :: 3
Requires-Python: <3.13,>=3.7
License-File: LICENSE
Requires-Dist: numpy<3.0,>=1.21
Requires-Dist: psutil
Provides-Extra: test
Requires-Dist: pytest>=7.4; extra == "test"
